Wordabulary/__init__.py
Wordabulary/__main__.py
Wordabulary/allstar_words.py
Wordabulary/anagrams.py
Wordabulary/booker.py
Wordabulary/booker_correct.py
Wordabulary/booker_most_frequent.py
Wordabulary/c06d.py
Wordabulary/c06d_guide.py
Wordabulary/crossword.py
Wordabulary/ends_with.py
Wordabulary/has_no_e.py
Wordabulary/has_no_these.py
Wordabulary/has_only_these.py
Wordabulary/histogram.py
Wordabulary/interlocked.py
Wordabulary/is_abecedarian.py
Wordabulary/is_there.py
Wordabulary/is_there_dict.py
Wordabulary/length_sorter.py
Wordabulary/plotters.py
Wordabulary/pronounce.py
Wordabulary/reverse_pairs.py
Wordabulary/rhyming.py
Wordabulary/rotate.py
Wordabulary/rotate_pairs.py
Wordabulary/wordabulary.py
Wordabulary/words_txt.py
Wordabulary/words_with_e.py
Wordabulary-1.0.5.dist-info/DESCRIPTION.rst
Wordabulary-1.0.5.dist-info/METADATA
Wordabulary-1.0.5.dist-info/RECORD
Wordabulary-1.0.5.dist-info/WHEEL
Wordabulary-1.0.5.dist-info/metadata.json
Wordabulary-1.0.5.dist-info/top_level.txt
