Metadata-Version: 2.0
Name: Wordabulary
Version: 1.0.5
Summary: A console-based software which may be used as a library for analysing word patterns, various properties of words, analysing documents.
Home-page: https://github.com/kaustubhhiware/Wordabulary
Author: Kaustubh Hiware
Author-email: hiwarekaustubh@gmail.com
License: GNU General Public License v3 (GPLv3)
Keywords: Words,Vocabulary,wordplay,Literature,Books,Kaustubh Hiware,Python
Platform: UNKNOWN
Classifier: Development Status :: 3 - Alpha
Classifier: Topic :: Software Development :: Build Tools
Classifier: Intended Audience :: Developers
Classifier: License :: OSI Approved :: GNU General Public License v3 (GPLv3)
Classifier: Programming Language :: Python :: 2.7
Requires-Dist: matplotlib
Requires-Dist: prettytable
